pysketcher/__init__.py
pysketcher/_angle.py
pysketcher/_arc.py
pysketcher/_arrow.py
pysketcher/_axis.py
pysketcher/_circle.py
pysketcher/_cubic_bezier_curve.py
pysketcher/_curve.py
pysketcher/_dashpot.py
pysketcher/_drawable.py
pysketcher/_figure.py
pysketcher/_force.py
pysketcher/_line.py
pysketcher/_moment.py
pysketcher/_point.py
pysketcher/_rectangle.py
pysketcher/_shape.py
pysketcher/_simple_support.py
pysketcher/_sketchy_func.py
pysketcher/_spline.py
pysketcher/_spring.py
pysketcher/_style.py
pysketcher/_text.py
pysketcher/_triangle.py
pysketcher/_uniform_load.py
pysketcher/_velocity_profile.py
pysketcher/_wall.py
pysketcher/_warning.py
pysketcher/_wheel.py
pysketcher/shapes.pyc
pysketcher/_utils/__init__.py
pysketcher/_utils/doc_enum.py
pysketcher/annotation/__init__.py
pysketcher/annotation/_arc_annotation.py
pysketcher/annotation/_line_annotation.py
pysketcher/annotation/_text_position.py
pysketcher/backend/__init__.py
pysketcher/backend/backend.py
pysketcher/backend/matplotlib/__init__.py
pysketcher/backend/matplotlib/_matplotlib_adapter.py
pysketcher/backend/matplotlib/_matplotlib_backend.py
pysketcher/backend/matplotlib/_matplotlib_composition.py
pysketcher/backend/matplotlib/_matplotlib_curve.py
pysketcher/backend/matplotlib/_matplotlib_style.py
pysketcher/backend/matplotlib/_matplotlib_text.py
pysketcher/composition/__init__.py
pysketcher/composition/_composition.py
pysketcher/dimension/__init__.py
pysketcher/dimension/_angular_dimension.py
pysketcher/dimension/_linear_dimension.py
pysketcher/dimension/_radial_dimension.py
pysketcher/images/.gitignore
pysketcher-0.0.13.dist-info/LICENSE
pysketcher-0.0.13.dist-info/METADATA
pysketcher-0.0.13.dist-info/WHEEL
pysketcher-0.0.13.dist-info/top_level.txt
pysketcher-0.0.13.dist-info/RECORD
