Metadata-Version: 2.1
Name: pysketcher
Version: 0.0.13
Summary: Geometric Sketching Utility for Python
Author: Hans Petter Langtangen
Author-email: Richard Vodden <richard@vodden.com>
License: MIT License
Project-URL: repository, https://github.com/rvodden/pysketcher.git
Project-URL: homepage, https://github.com/rvodden/pysketcher
Keywords: sketch,graphics,scientific,engineering,geometry
Requires-Python: <4,>=3.11
License-File: LICENSE
Requires-Dist: numpy<2.3,>=1.25
Requires-Dist: matplotlib<3.11.0,>=3.7.1
Requires-Dist: scipy<1.15.0,>=1.10.1
Requires-Dist: celluloid~=0.2.0
Provides-Extra: build
Requires-Dist: build; extra == "build"
Requires-Dist: twine; extra == "build"
Requires-Dist: nox; extra == "build"
Provides-Extra: tests
Requires-Dist: hypothesis<6.124.0,>=6.104.1; extra == "tests"
Requires-Dist: pytest<8.4.0,>=8.2.2; extra == "tests"
Requires-Dist: coverage<7.7.0,>=7.2.7; extra == "tests"
Requires-Dist: mypy<2.0,>=0.991; extra == "tests"
Requires-Dist: wheel<0.46.0,>=0.38.4; extra == "tests"
Requires-Dist: pytest-cov<6.1,>=4.0; extra == "tests"
Requires-Dist: pytest-timeout<2.4,>=2.1; extra == "tests"
Requires-Dist: nox-poetry~=1.0.2; extra == "tests"
Requires-Dist: flake8-docstrings<1.8,>=1.6; extra == "tests"
Requires-Dist: flake8-bugbear<24.13.0,>=24.4.26; extra == "tests"
Requires-Dist: codecov~=2.1.10; extra == "tests"
Provides-Extra: lint
Requires-Dist: pylint<3.4.0,>=3.2.5; extra == "lint"
Requires-Dist: flake8<7.2.0,>=5.0.4; extra == "lint"
Requires-Dist: pydocstyle<6.4.0,>=6.1.1; extra == "lint"
Requires-Dist: black<24.11,>=23.3; extra == "lint"
Requires-Dist: flake8-black~=0.3.6; extra == "lint"
Requires-Dist: flake8-import-order~=0.18.2; extra == "lint"
Requires-Dist: flake8-bandit~=4.1.1; extra == "lint"
Requires-Dist: darglint<1.9,>=1.7; extra == "lint"
Requires-Dist: blackdoc~=0.3; extra == "lint"
Provides-Extra: precommit
Requires-Dist: pre-commit<4.1,>=2.21; extra == "precommit"
Requires-Dist: commitizen<4.2.0,>=2.39.1; extra == "precommit"
Provides-Extra: documentation
Requires-Dist: sphinx<8.1.0,>=7.3.7; extra == "documentation"
Requires-Dist: furo<2024.9.0,>=2023.5.20; extra == "documentation"
Requires-Dist: sphinx-autodoc-typehints<3.1.0,>=2.2.2; extra == "documentation"
Requires-Dist: recommonmark~=0.7.1; extra == "documentation"
